myweather/__init__.py
myweather/myweather.py
myweather-0.7.0.dist-info/METADATA
myweather-0.7.0.dist-info/WHEEL
myweather-0.7.0.dist-info/licenses/LICENSE
myweather-0.7.0.dist-info/RECORD
